volcenginesdkacep
volcenginesdkadvdefence
volcenginesdkadvdefence20230308
volcenginesdkaiotvideo
volcenginesdkaiotvideo20231001
volcenginesdkalb
volcenginesdkapig
volcenginesdkapig20221112
volcenginesdkark
volcenginesdkarkruntime
volcenginesdkautoscaling
volcenginesdkbilling
volcenginesdkbio
volcenginesdkbmq
volcenginesdkbmq20240901
volcenginesdkbytehousece20240831
volcenginesdkcbr
volcenginesdkcdn
volcenginesdkcen
volcenginesdkcertificateservice
volcenginesdkcfs
volcenginesdkclb
volcenginesdkclouddetect
volcenginesdkclouddetect20251031
volcenginesdkcloudidentity
volcenginesdkcloudmonitor
volcenginesdkcloudtrail
volcenginesdkcloudtrail20180101
volcenginesdkconfig
volcenginesdkcore
volcenginesdkcoze20250601
volcenginesdkcr
volcenginesdkcv20240606
volcenginesdkdataleap
volcenginesdkdbw
volcenginesdkdirectconnect
volcenginesdkdms
volcenginesdkdms20250101
volcenginesdkdns
volcenginesdkdts
volcenginesdkdts20180101
volcenginesdkecs
volcenginesdkedx
volcenginesdkefs
volcenginesdkemr
volcenginesdkescloud
volcenginesdkfasttrack
volcenginesdkfilenas
volcenginesdkflink20250101
volcenginesdkfwcenter
volcenginesdkga
volcenginesdkgraph
volcenginesdkgraph20250815
volcenginesdkhbase
volcenginesdkhttpdns
volcenginesdki18nopenapi
volcenginesdkiam
volcenginesdkiam20210801
volcenginesdkid
volcenginesdkinsight
volcenginesdkkafka
volcenginesdkkms
volcenginesdklivesaas
volcenginesdklivesaas20230801
volcenginesdkllmscan
volcenginesdkllmshield
volcenginesdkmcdn
volcenginesdkmcs
volcenginesdkmetakms
volcenginesdkmilvus
volcenginesdkmlplatform20240701
volcenginesdkmongodb
volcenginesdkna
volcenginesdknatgateway
volcenginesdknta
volcenginesdkorganization
volcenginesdkpca
volcenginesdkpca20251001
volcenginesdkprivatelink
volcenginesdkprivatezone
volcenginesdkquota
volcenginesdkrabbitmq
volcenginesdkrcs5g
volcenginesdkrdsmssql
volcenginesdkrdsmysql
volcenginesdkrdsmysqlv2
volcenginesdkrdspostgresql
volcenginesdkredis
volcenginesdkresourcecenter
volcenginesdkresourceshare
volcenginesdkrocketmq
