Metadata-Version: 2.4
Name: volcengine-python-sdk
Version: 5.0.7
Summary: Volcengine SDK for Python
Home-page: https://github.com/volcengine/volcengine-python-sdk
Author-email: volc-engine <volc-sdk-team@bytedance.com>
License-Expression: Apache-2.0
Keywords: volcengine,sdk
Platform: any
Requires-Python: >=2.7
License-File: LICENSE.txt
License-File: NOTICE.md
Requires-Dist: certifi>=2017.4.17
Requires-Dist: python-dateutil>=2.1
Requires-Dist: six>=1.16
Requires-Dist: urllib3>=1.26.5
Provides-Extra: ark
Requires-Dist: pydantic<3,>=1.9.0; extra == "ark"
Requires-Dist: httpx<1,>=0.23.0; extra == "ark"
Requires-Dist: anyio<5,>=3.5.0; extra == "ark"
Requires-Dist: cached-property; python_version < "3.8" and extra == "ark"
Requires-Dist: cryptography>=44.0.1; extra == "ark"
Dynamic: home-page
Dynamic: license-file
Dynamic: platform
